datav/__init__.py
datav/downloader.py
datav/feature.py
datav/plot.py
datav-0.2.1.dist-info/METADATA
datav-0.2.1.dist-info/WHEEL
datav-0.2.1.dist-info/licenses/LICENSE
datav-0.2.1.dist-info/RECORD
