Metadata-Version: 2.3
Name: datav
Version: 0.2.1
Summary: Data visualization tools for Python.
Author-email: Tang Ziya <tcztzy@gmail.com>
License:                    GNU LESSER GENERAL PUBLIC LICENSE
License-File: LICENSE
Classifier: Framework :: Matplotlib
Classifier: Intended Audience :: Education
Classifier: Intended Audience :: Science/Research
Classifier: License :: Free For Educational Use
Classifier: License :: OSI Approved :: GNU Lesser General Public License v3 or later (LGPLv3+)
Classifier: Natural Language :: Chinese (Simplified)
Classifier: Programming Language :: Python :: 3 :: Only
Classifier: Programming Language :: Python :: 3.9
Classifier: Programming Language :: Python :: 3.10
Classifier: Programming Language :: Python :: 3.11
Classifier: Programming Language :: Python :: 3.12
Requires-Python: >=3.9
Requires-Dist: cartopy>=0.23
Requires-Dist: geopandas>=1.0.1
Requires-Dist: matplotlib>=3.9.2
Requires-Dist: numpy>=2
Requires-Dist: scikit-learn>=1.5.2
Requires-Dist: xarray>=2024.7.0
